setup.py
zmqrpc/__init__.py
zmqrpc/client.py
zmqrpc/server.py
zmqrpc.egg-info/PKG-INFO
zmqrpc.egg-info/SOURCES.txt
zmqrpc.egg-info/dependency_links.txt
zmqrpc.egg-info/requires.txt
zmqrpc.egg-info/top_level.txt