Metadata-Version: 1.0
Name: zmqrpc
Version: 0.1f
Summary: A Python library that exports a class for RPC via zmq, using BSON for data interchange.
Home-page: https://github.com/geoffwatts/zmqrpc
Author: Geoff Watts
Author-email: geoff@editd.com
License: UNKNOWN
Platform: UNKNOWN
